docido_sdk/__init__.py
docido_sdk/config.py
docido_sdk/core.py
docido_sdk/env.py
docido_sdk/loader.py
docido_sdk/crawler/__init__.py
docido_sdk/crawler/api.py
docido_sdk/crawler/errors.py
docido_sdk/crawler/tasks.py
docido_sdk/index/__init__.py
docido_sdk/index/api.py
docido_sdk/index/config.py
docido_sdk/index/errors.py
docido_sdk/index/helpers.py
docido_sdk/index/pipeline.py
docido_sdk/index/test.py
docido_sdk/index/processor/__init__.py
docido_sdk/index/processor/check.py
docido_sdk/index/processor/es_api.py
docido_sdk/oauth/__init__.py
docido_sdk/oauth/api.py
docido_sdk/scripts/__init__.py
docido_sdk/scripts/dcc_run.py
docido_sdk/test/__init__.py
docido_sdk/toolbox/__init__.py
docido_sdk/toolbox/collections_ext.py
docido_sdk/toolbox/contextlib_ext.py
docido_sdk/toolbox/date_ext.py
docido_sdk/toolbox/decorators.py
docido_sdk/toolbox/edsl.py
docido_sdk/toolbox/file_ext.py
docido_sdk/toolbox/google_ext.py
docido_sdk/toolbox/http_ext.py
docido_sdk/toolbox/loader.py
docido_sdk/toolbox/rate_limits.py
docido_sdk/toolbox/text.py
docido_sdk/toolbox/threading_ext.py
docido_sdk/toolbox/yaml_ext.py
docido_sdk-0.0.32.dist-info/DESCRIPTION.rst
docido_sdk-0.0.32.dist-info/entry_points.txt
docido_sdk-0.0.32.dist-info/METADATA
docido_sdk-0.0.32.dist-info/metadata.json
docido_sdk-0.0.32.dist-info/RECORD
docido_sdk-0.0.32.dist-info/top_level.txt
docido_sdk-0.0.32.dist-info/WHEEL
docido_sdk-0.0.32.dist-info/zip-safe
