Metadata-Version: 2.0
Name: docido-sdk
Version: 0.0.32
Summary: Docido software development kit for Python
Home-page: https://github.com/cogniteev/docido-python-sdk
Author: Cogniteev
Author-email: tech@cogniteev.com
License: Apache license version 2.0
Download-URL: https://github.com/cogniteev/docido-python-sdk/tarball/0.0.32
Keywords: cogniteev docido
Platform: UNKNOWN
Classifier: Development Status :: 2 - Pre-Alpha
Classifier: Intended Audience :: Developers
Classifier: License :: OSI Approved :: Apache Software License
Classifier: Topic :: Software Development :: Libraries
Classifier: Topic :: Internet :: WWW/HTTP :: Indexing/Search
Classifier: Programming Language :: Python
Classifier: Programming Language :: Python :: 2.7
Classifier: Operating System :: OS Independent
Classifier: Natural Language :: English
Requires-Dist: elasticsearch (==2.3.0)
Requires-Dist: ProxyTypes (==0.9)
Requires-Dist: python-dateutil (>=2.5.2)
Requires-Dist: pytz (>=2015.6)
Requires-Dist: requests (>=2.8.1)
Requires-Dist: setuptools (>=0.6)
Requires-Dist: six (>=1.10.0)
Requires-Dist: yamlious (>=0.2.1)
